<?xml version="1.0" encoding="UTF-8"?>
<qes:espresso xsi:schemaLocation="http://www.quantum-espresso.org/ns/qes/qes-1.0 http://www.quantum-espresso.org/ns/qes/qes_190304.xsd" Units="Hartree atomic units" xmlns:xsi="http://www.w3.org/2001/XMLSchema-instance" xmlns:qes="http://www.quantum-espresso.org/ns/qes/qes-1.0">
  <!--If not explicitely indicated, all quantities are expressed in Hartree atomic units-->
  <general_info>
    <xml_format NAME="QEXSD" VERSION="19.03">QEXSD_19.03</xml_format>
    <creator NAME="PWSCF" VERSION="6.4.1">XML file generated by PWSCF</creator>
    <created DATE="31Jul2021" TIME="15:42:31">This run was terminated on:  15:42:31  31 Jul 2021</created>
    <job></job>
  </general_info>
  <parallel_info>
    <nprocs>1</nprocs>
    <nthreads>1</nthreads>
    <ntasks>1</ntasks>
    <nbgrp>1</nbgrp>
    <npool>1</npool>
    <ndiag>1</ndiag>
  </parallel_info>
  <input>
    <control_variables>
      <title></title>
      <calculation>scf</calculation>
      <restart_mode>from_scratch</restart_mode>
      <prefix>sto</prefix>
      <pseudo_dir>./</pseudo_dir>
      <outdir>./</outdir>
      <stress>false</stress>
      <forces>false</forces>
      <wf_collect>true</wf_collect>
      <disk_io>low</disk_io>
      <max_seconds>10000000</max_seconds>
      <nstep>1</nstep>
      <etot_conv_thr>5.000000000000000e-5</etot_conv_thr>
      <forc_conv_thr>5.000000000000000e-4</forc_conv_thr>
      <press_conv_thr>5.000000000000000e-1</press_conv_thr>
      <verbosity>low</verbosity>
      <print_every>100000</print_every>
    </control_variables>
    <atomic_species ntyp="3">
      <species name="Sr">
        <mass>8.762000000000000e1</mass>
        <pseudo_file>Sr.pz-hgh.UPF</pseudo_file>
      </species>
      <species name="Ti">
        <mass>4.797000000000000e1</mass>
        <pseudo_file>Ti.pz-hgh.UPF</pseudo_file>
      </species>
      <species name="O">
        <mass>1.600000000000000e1</mass>
        <pseudo_file>O.pz-hgh.UPF</pseudo_file>
      </species>
    </atomic_species>
    <atomic_structure nat="5" alat="7.154334000000e0">
      <atomic_positions>
        <atom name="Sr" index="1">0.000000000000000e0 0.000000000000000e0 0.000000000000000e0</atom>
        <atom name="Ti" index="2">3.577167000000000e0 3.577167000000000e0 3.577167000000000e0</atom>
        <atom name="O" index="3">3.577167000000000e0 0.000000000000000e0 3.577167000000000e0</atom>
        <atom name="O" index="4">3.577167000000000e0 3.577167000000000e0 0.000000000000000e0</atom>
        <atom name="O" index="5">0.000000000000000e0 3.577167000000000e0 3.577167000000000e0</atom>
      </atomic_positions>
      <cell>
        <a1>7.154334000000000e0 0.000000000000000e0 0.000000000000000e0</a1>
        <a2>0.000000000000000e0 7.154334000000000e0 0.000000000000000e0</a2>
        <a3>0.000000000000000e0 0.000000000000000e0 7.154334000000000e0</a3>
      </cell>
    </atomic_structure>
    <dft>
      <functional>PZ</functional>
    </dft>
    <spin>
      <lsda>false</lsda>
      <noncolin>false</noncolin>
      <spinorbit>false</spinorbit>
    </spin>
    <bands>
      <tot_charge>0.000000000000000e0</tot_charge>
      <occupations>fixed</occupations>
    </bands>
    <basis>
      <gamma_only>false</gamma_only>
      <ecutwfc>1.050000000000000e2</ecutwfc>
      <ecutrho>4.200000000000000e2</ecutrho>
    </basis>
    <electron_control>
      <diagonalization>davidson</diagonalization>
      <mixing_mode>plain</mixing_mode>
      <mixing_beta>7.000000000000000e-1</mixing_beta>
      <conv_thr>5.000000000000000e-7</conv_thr>
      <mixing_ndim>8</mixing_ndim>
      <max_nstep>100</max_nstep>
      <real_space_q>false</real_space_q>
      <real_space_beta>false</real_space_beta>
      <tq_smoothing>false</tq_smoothing>
      <tbeta_smoothing>false</tbeta_smoothing>
      <diago_thr_init>0.000000000000000e0</diago_thr_init>
      <diago_full_acc>false</diago_full_acc>
      <diago_cg_maxiter>20</diago_cg_maxiter>
      <diago_ppcg_maxiter>20</diago_ppcg_maxiter>
      <diago_rmm_ndim>4</diago_rmm_ndim>
      <diago_rmm_conv>false</diago_rmm_conv>
      <diago_gs_nblock>16</diago_gs_nblock>
    </electron_control>
    <k_points_IBZ>
      <monkhorst_pack nk1="4" nk2="4" nk3="4" k1="1" k2="1" k3="1">Uniform grid with offset</monkhorst_pack>
    </k_points_IBZ>
    <ion_control>
      <ion_dynamics>none</ion_dynamics>
      <upscale>1.000000000000000e2</upscale>
      <remove_rigid_rot>false</remove_rigid_rot>
      <refold_pos>false</refold_pos>
    </ion_control>
    <cell_control>
      <cell_dynamics>none</cell_dynamics>
      <pressure>0.000000000000000e0</pressure>
      <wmass>1.673320484130640e5</wmass>
      <cell_factor>0.000000000000000e0</cell_factor>
      <fix_volume>false</fix_volume>
      <fix_area>false</fix_area>
      <isotropic>false</isotropic>
    </cell_control>
    <symmetry_flags>
      <nosym>false</nosym>
      <nosym_evc>false</nosym_evc>
      <noinv>false</noinv>
      <no_t_rev>false</no_t_rev>
      <force_symmorphic>false</force_symmorphic>
      <use_all_frac>false</use_all_frac>
    </symmetry_flags>
  </input>
  <output>
    <convergence_info>
      <scf_conv>
        <convergence_achieved>false</convergence_achieved>
        <n_scf_steps>30</n_scf_steps>
        <scf_error>3.979069796351347e-7</scf_error>
      </scf_conv>
    </convergence_info>
    <algorithmic_info>
      <real_space_q>false</real_space_q>
      <real_space_beta>false</real_space_beta>
      <uspp>false</uspp>
      <paw>false</paw>
    </algorithmic_info>
    <atomic_species ntyp="3" pseudo_dir="./\">
      <species name="Sr">
        <mass>8.762000000000000e1</mass>
        <pseudo_file>Sr.pz-hgh.UPF</pseudo_file>
      </species>
      <species name="Ti">
        <mass>4.797000000000000e1</mass>
        <pseudo_file>Ti.pz-hgh.UPF</pseudo_file>
      </species>
      <species name="O">
        <mass>1.600000000000000e1</mass>
        <pseudo_file>O.pz-hgh.UPF</pseudo_file>
      </species>
    </atomic_species>
    <atomic_structure nat="5" alat="7.226600000000e0">
      <atomic_positions>
        <atom name="Sr" index="1">0.000000000000000e0 0.000000000000000e0 0.000000000000000e0</atom>
        <atom name="Ti" index="2">3.577167000000000e0 3.577167000000000e0 3.577167000000000e0</atom>
        <atom name="O" index="3">3.577167000000000e0 0.000000000000000e0 3.577167000000000e0</atom>
        <atom name="O" index="4">3.577167000000000e0 3.577167000000000e0 0.000000000000000e0</atom>
        <atom name="O" index="5">0.000000000000000e0 3.577167000000000e0 3.577167000000000e0</atom>
      </atomic_positions>
      <cell>
        <a1>7.154334000000000e0 0.000000000000000e0 0.000000000000000e0</a1>
        <a2>0.000000000000000e0 7.154334000000000e0 0.000000000000000e0</a2>
        <a3>0.000000000000000e0 0.000000000000000e0 7.154334000000000e0</a3>
      </cell>
    </atomic_structure>
    <symmetries>
      <nsym>48</nsym>
      <nrot>48</nrot>
      <space_group>0</space_group>
      <symmetry>
        <info name="identity">crystal_symmetry</info>
        <rotation rank="2" dims="3 3" order="F">
          1.000000000000000e0 0.000000000000000e0 0.000000000000000e0
          0.000000000000000e0 1.000000000000000e0 0.000000000000000e0
          0.000000000000000e0 0.000000000000000e0 1.000000000000000e0
          </rotation>
        <fractional_translation>0.000000000000000e0 0.000000000000000e0 0.000000000000000e0</fractional_translation>
        <equivalent_atoms nat="5" size="5">
          1 2 3 4 5
          </equivalent_atoms>
      </symmetry>
      <symmetry>
        <info name="180 deg rotation - cart. axis [0,0,1]">crystal_symmetry</info>
        <rotation rank="2" dims="3 3" order="F">
          -1.000000000000000e0 0.000000000000000e0 0.000000000000000e0
          0.000000000000000e0 -1.000000000000000e0 0.000000000000000e0
          0.000000000000000e0 0.000000000000000e0 1.000000000000000e0
          </rotation>
        <fractional_translation>0.000000000000000e0 0.000000000000000e0 0.000000000000000e0</fractional_translation>
        <equivalent_atoms nat="5" size="5">
          1 2 3 4 5
          </equivalent_atoms>
      </symmetry>
      <symmetry>
        <info name="180 deg rotation - cart. axis [0,1,0]">crystal_symmetry</info>
        <rotation rank="2" dims="3 3" order="F">
          -1.000000000000000e0 0.000000000000000e0 0.000000000000000e0
          0.000000000000000e0 1.000000000000000e0 0.000000000000000e0
          0.000000000000000e0 0.000000000000000e0 -1.000000000000000e0
          </rotation>
        <fractional_translation>0.000000000000000e0 0.000000000000000e0 0.000000000000000e0</fractional_translation>
        <equivalent_atoms nat="5" size="5">
          1 2 3 4 5
          </equivalent_atoms>
      </symmetry>
      <symmetry>
        <info name="180 deg rotation - cart. axis [1,0,0]">crystal_symmetry</info>
        <rotation rank="2" dims="3 3" order="F">
          1.000000000000000e0 0.000000000000000e0 0.000000000000000e0
          0.000000000000000e0 -1.000000000000000e0 0.000000000000000e0
          0.000000000000000e0 0.000000000000000e0 -1.000000000000000e0
          </rotation>
        <fractional_translation>0.000000000000000e0 0.000000000000000e0 0.000000000000000e0</fractional_translation>
        <equivalent_atoms nat="5" size="5">
          1 2 3 4 5
          </equivalent_atoms>
      </symmetry>
      <symmetry>
        <info name="180 deg rotation - cart. axis [1,1,0]">crystal_symmetry</info>
        <rotation rank="2" dims="3 3" order="F">
          0.000000000000000e0 1.000000000000000e0 0.000000000000000e0
          1.000000000000000e0 0.000000000000000e0 0.000000000000000e0
          0.000000000000000e0 0.000000000000000e0 -1.000000000000000e0
          </rotation>
        <fractional_translation>0.000000000000000e0 0.000000000000000e0 0.000000000000000e0</fractional_translation>
        <equivalent_atoms nat="5" size="5">
          1 2 5 4 3
          </equivalent_atoms>
      </symmetry>
      <symmetry>
        <info name="180 deg rotation - cart. axis [1,-1,0]">crystal_symmetry</info>
        <rotation rank="2" dims="3 3" order="F">
          0.000000000000000e0 -1.000000000000000e0 0.000000000000000e0
          -1.000000000000000e0 0.000000000000000e0 0.000000000000000e0
          0.000000000000000e0 0.000000000000000e0 -1.000000000000000e0
          </rotation>
        <fractional_translation>0.000000000000000e0 0.000000000000000e0 0.000000000000000e0</fractional_translation>
        <equivalent_atoms nat="5" size="5">
          1 2 5 4 3
          </equivalent_atoms>
      </symmetry>
      <symmetry>
        <info name=" 90 deg rotation - cart. axis [0,0,-1]">crystal_symmetry</info>
        <rotation rank="2" dims="3 3" order="F">
          0.000000000000000e0 1.000000000000000e0 0.000000000000000e0
          -1.000000000000000e0 0.000000000000000e0 0.000000000000000e0
          0.000000000000000e0 0.000000000000000e0 1.000000000000000e0
          </rotation>
        <fractional_translation>0.000000000000000e0 0.000000000000000e0 0.000000000000000e0</fractional_translation>
        <equivalent_atoms nat="5" size="5">
          1 2 5 4 3
          </equivalent_atoms>
      </symmetry>
      <symmetry>
        <info name=" 90 deg rotation - cart. axis [0,0,1]">crystal_symmetry</info>
        <rotation rank="2" dims="3 3" order="F">
          0.000000000000000e0 -1.000000000000000e0 0.000000000000000e0
          1.000000000000000e0 0.000000000000000e0 0.000000000000000e0
          0.000000000000000e0 0.000000000000000e0 1.000000000000000e0
          </rotation>
        <fractional_translation>0.000000000000000e0 0.000000000000000e0 0.000000000000000e0</fractional_translation>
        <equivalent_atoms nat="5" size="5">
          1 2 5 4 3
          </equivalent_atoms>
      </symmetry>
      <symmetry>
        <info name="180 deg rotation - cart. axis [1,0,1]">crystal_symmetry</info>
        <rotation rank="2" dims="3 3" order="F">
          0.000000000000000e0 0.000000000000000e0 1.000000000000000e0
          0.000000000000000e0 -1.000000000000000e0 0.000000000000000e0
          1.000000000000000e0 0.000000000000000e0 0.000000000000000e0
          </rotation>
        <fractional_translation>0.000000000000000e0 0.000000000000000e0 0.000000000000000e0</fractional_translation>
        <equivalent_atoms nat="5" size="5">
          1 2 3 5 4
          </equivalent_atoms>
      </symmetry>
      <symmetry>
        <info name="180 deg rotation - cart. axis [-1,0,1]">crystal_symmetry</info>
        <rotation rank="2" dims="3 3" order="F">
          0.000000000000000e0 0.000000000000000e0 -1.000000000000000e0
          0.000000000000000e0 -1.000000000000000e0 0.000000000000000e0
          -1.000000000000000e0 0.000000000000000e0 0.000000000000000e0
          </rotation>
        <fractional_translation>0.000000000000000e0 0.000000000000000e0 0.000000000000000e0</fractional_translation>
        <equivalent_atoms nat="5" size="5">
          1 2 3 5 4
          </equivalent_atoms>
      </symmetry>
      <symmetry>
        <info name=" 90 deg rotation - cart. axis [0,1,0]">crystal_symmetry</info>
        <rotation rank="2" dims="3 3" order="F">
          0.000000000000000e0 0.000000000000000e0 1.000000000000000e0
          0.000000000000000e0 1.000000000000000e0 0.000000000000000e0
          -1.000000000000000e0 0.000000000000000e0 0.000000000000000e0
          </rotation>
        <fractional_translation>0.000000000000000e0 0.000000000000000e0 0.000000000000000e0</fractional_translation>
        <equivalent_atoms nat="5" size="5">
          1 2 3 5 4
          </equivalent_atoms>
      </symmetry>
      <symmetry>
        <info name=" 90 deg rotation - cart. axis [0,-1,0]">crystal_symmetry</info>
        <rotation rank="2" dims="3 3" order="F">
          0.000000000000000e0 0.000000000000000e0 -1.000000000000000e0
          0.000000000000000e0 1.000000000000000e0 0.000000000000000e0
          1.000000000000000e0 0.000000000000000e0 0.000000000000000e0
          </rotation>
        <fractional_translation>0.000000000000000e0 0.000000000000000e0 0.000000000000000e0</fractional_translation>
        <equivalent_atoms nat="5" size="5">
          1 2 3 5 4
          </equivalent_atoms>
      </symmetry>
      <symmetry>
        <info name="180 deg rotation - cart. axis [0,1,1]">crystal_symmetry</info>
        <rotation rank="2" dims="3 3" order="F">
          -1.000000000000000e0 0.000000000000000e0 0.000000000000000e0
          0.000000000000000e0 0.000000000000000e0 1.000000000000000e0
          0.000000000000000e0 1.000000000000000e0 0.000000000000000e0
          </rotation>
        <fractional_translation>0.000000000000000e0 0.000000000000000e0 0.000000000000000e0</fractional_translation>
        <equivalent_atoms nat="5" size="5">
          1 2 4 3 5
          </equivalent_atoms>
      </symmetry>
      <symmetry>
        <info name="180 deg rotation - cart. axis [0,1,-1]">crystal_symmetry</info>
        <rotation rank="2" dims="3 3" order="F">
          -1.000000000000000e0 0.000000000000000e0 0.000000000000000e0
          0.000000000000000e0 0.000000000000000e0 -1.000000000000000e0
          0.000000000000000e0 -1.000000000000000e0 0.000000000000000e0
          </rotation>
        <fractional_translation>0.000000000000000e0 0.000000000000000e0 0.000000000000000e0</fractional_translation>
        <equivalent_atoms nat="5" size="5">
          1 2 4 3 5
          </equivalent_atoms>
      </symmetry>
      <symmetry>
        <info name=" 90 deg rotation - cart. axis [-1,0,0]">crystal_symmetry</info>
        <rotation rank="2" dims="3 3" order="F">
          1.000000000000000e0 0.000000000000000e0 0.000000000000000e0
          0.000000000000000e0 0.000000000000000e0 1.000000000000000e0
          0.000000000000000e0 -1.000000000000000e0 0.000000000000000e0
          </rotation>
        <fractional_translation>0.000000000000000e0 0.000000000000000e0 0.000000000000000e0</fractional_translation>
        <equivalent_atoms nat="5" size="5">
          1 2 4 3 5
          </equivalent_atoms>
      </symmetry>
      <symmetry>
        <info name=" 90 deg rotation - cart. axis [1,0,0]">crystal_symmetry</info>
        <rotation rank="2" dims="3 3" order="F">
          1.000000000000000e0 0.000000000000000e0 0.000000000000000e0
          0.000000000000000e0 0.000000000000000e0 -1.000000000000000e0
          0.000000000000000e0 1.000000000000000e0 0.000000000000000e0
          </rotation>
        <fractional_translation>0.000000000000000e0 0.000000000000000e0 0.000000000000000e0</fractional_translation>
        <equivalent_atoms nat="5" size="5">
          1 2 4 3 5
          </equivalent_atoms>
      </symmetry>
      <symmetry>
        <info name="120 deg rotation - cart. axis [-1,-1,-1]">crystal_symmetry</info>
        <rotation rank="2" dims="3 3" order="F">
          0.000000000000000e0 1.000000000000000e0 0.000000000000000e0
          0.000000000000000e0 0.000000000000000e0 1.000000000000000e0
          1.000000000000000e0 0.000000000000000e0 0.000000000000000e0
          </rotation>
        <fractional_translation>0.000000000000000e0 0.000000000000000e0 0.000000000000000e0</fractional_translation>
        <equivalent_atoms nat="5" size="5">
          1 2 5 3 4
          </equivalent_atoms>
      </symmetry>
      <symmetry>
        <info name="120 deg rotation - cart. axis [-1,1,1]">crystal_symmetry</info>
        <rotation rank="2" dims="3 3" order="F">
          0.000000000000000e0 -1.000000000000000e0 0.000000000000000e0
          0.000000000000000e0 0.000000000000000e0 1.000000000000000e0
          -1.000000000000000e0 0.000000000000000e0 0.000000000000000e0
          </rotation>
        <fractional_translation>0.000000000000000e0 0.000000000000000e0 0.000000000000000e0</fractional_translation>
        <equivalent_atoms nat="5" size="5">
          1 2 5 3 4
          </equivalent_atoms>
      </symmetry>
      <symmetry>
        <info name="120 deg rotation - cart. axis [1,1,-1]">crystal_symmetry</info>
        <rotation rank="2" dims="3 3" order="F">
          0.000000000000000e0 1.000000000000000e0 0.000000000000000e0
          0.000000000000000e0 0.000000000000000e0 -1.000000000000000e0
          -1.000000000000000e0 0.000000000000000e0 0.000000000000000e0
          </rotation>
        <fractional_translation>0.000000000000000e0 0.000000000000000e0 0.000000000000000e0</fractional_translation>
        <equivalent_atoms nat="5" size="5">
          1 2 5 3 4
          </equivalent_atoms>
      </symmetry>
      <symmetry>
        <info name="120 deg rotation - cart. axis [1,-1,1]">crystal_symmetry</info>
        <rotation rank="2" dims="3 3" order="F">
          0.000000000000000e0 -1.000000000000000e0 0.000000000000000e0
          0.000000000000000e0 0.000000000000000e0 -1.000000000000000e0
          1.000000000000000e0 0.000000000000000e0 0.000000000000000e0
          </rotation>
        <fractional_translation>0.000000000000000e0 0.000000000000000e0 0.000000000000000e0</fractional_translation>
        <equivalent_atoms nat="5" size="5">
          1 2 5 3 4
          </equivalent_atoms>
      </symmetry>
      <symmetry>
        <info name="120 deg rotation - cart. axis [1,1,1]">crystal_symmetry</info>
        <rotation rank="2" dims="3 3" order="F">
          0.000000000000000e0 0.000000000000000e0 1.000000000000000e0
          1.000000000000000e0 0.000000000000000e0 0.000000000000000e0
          0.000000000000000e0 1.000000000000000e0 0.000000000000000e0
          </rotation>
        <fractional_translation>0.000000000000000e0 0.000000000000000e0 0.000000000000000e0</fractional_translation>
        <equivalent_atoms nat="5" size="5">
          1 2 4 5 3
          </equivalent_atoms>
      </symmetry>
      <symmetry>
        <info name="120 deg rotation - cart. axis [-1,1,-1]">crystal_symmetry</info>
        <rotation rank="2" dims="3 3" order="F">
          0.000000000000000e0 0.000000000000000e0 1.000000000000000e0
          -1.000000000000000e0 0.000000000000000e0 0.000000000000000e0
          0.000000000000000e0 -1.000000000000000e0 0.000000000000000e0
          </rotation>
        <fractional_translation>0.000000000000000e0 0.000000000000000e0 0.000000000000000e0</fractional_translation>
        <equivalent_atoms nat="5" size="5">
          1 2 4 5 3
          </equivalent_atoms>
      </symmetry>
      <symmetry>
        <info name="120 deg rotation - cart. axis [1,-1,-1]">crystal_symmetry</info>
        <rotation rank="2" dims="3 3" order="F">
          0.000000000000000e0 0.000000000000000e0 -1.000000000000000e0
          -1.000000000000000e0 0.000000000000000e0 0.000000000000000e0
          0.000000000000000e0 1.000000000000000e0 0.000000000000000e0
          </rotation>
        <fractional_translation>0.000000000000000e0 0.000000000000000e0 0.000000000000000e0</fractional_translation>
        <equivalent_atoms nat="5" size="5">
          1 2 4 5 3
          </equivalent_atoms>
      </symmetry>
      <symmetry>
        <info name="120 deg rotation - cart. axis [-1,-1,1]">crystal_symmetry</info>
        <rotation rank="2" dims="3 3" order="F">
          0.000000000000000e0 0.000000000000000e0 -1.000000000000000e0
          1.000000000000000e0 0.000000000000000e0 0.000000000000000e0
          0.000000000000000e0 -1.000000000000000e0 0.000000000000000e0
          </rotation>
        <fractional_translation>0.000000000000000e0 0.000000000000000e0 0.000000000000000e0</fractional_translation>
        <equivalent_atoms nat="5" size="5">
          1 2 4 5 3
          </equivalent_atoms>
      </symmetry>
      <symmetry>
        <info name="inversion">crystal_symmetry</info>
        <rotation rank="2" dims="3 3" order="F">
          -1.000000000000000e0 0.000000000000000e0 0.000000000000000e0
          0.000000000000000e0 -1.000000000000000e0 0.000000000000000e0
          0.000000000000000e0 0.000000000000000e0 -1.000000000000000e0
          </rotation>
        <fractional_translation>0.000000000000000e0 0.000000000000000e0 0.000000000000000e0</fractional_translation>
        <equivalent_atoms nat="5" size="5">
          1 2 3 4 5
          </equivalent_atoms>
      </symmetry>
      <symmetry>
        <info name="inv. 180 deg rotation - cart. axis [0,0,1]">crystal_symmetry</info>
        <rotation rank="2" dims="3 3" order="F">
          1.000000000000000e0 0.000000000000000e0 0.000000000000000e0
          0.000000000000000e0 1.000000000000000e0 0.000000000000000e0
          0.000000000000000e0 0.000000000000000e0 -1.000000000000000e0
          </rotation>
        <fractional_translation>0.000000000000000e0 0.000000000000000e0 0.000000000000000e0</fractional_translation>
        <equivalent_atoms nat="5" size="5">
          1 2 3 4 5
          </equivalent_atoms>
      </symmetry>
      <symmetry>
        <info name="inv. 180 deg rotation - cart. axis [0,1,0]">crystal_symmetry</info>
        <rotation rank="2" dims="3 3" order="F">
          1.000000000000000e0 0.000000000000000e0 0.000000000000000e0
          0.000000000000000e0 -1.000000000000000e0 0.000000000000000e0
          0.000000000000000e0 0.000000000000000e0 1.000000000000000e0
          </rotation>
        <fractional_translation>0.000000000000000e0 0.000000000000000e0 0.000000000000000e0</fractional_translation>
        <equivalent_atoms nat="5" size="5">
          1 2 3 4 5
          </equivalent_atoms>
      </symmetry>
      <symmetry>
        <info name="inv. 180 deg rotation - cart. axis [1,0,0]">crystal_symmetry</info>
        <rotation rank="2" dims="3 3" order="F">
          -1.000000000000000e0 0.000000000000000e0 0.000000000000000e0
          0.000000000000000e0 1.000000000000000e0 0.000000000000000e0
          0.000000000000000e0 0.000000000000000e0 1.000000000000000e0
          </rotation>
        <fractional_translation>0.000000000000000e0 0.000000000000000e0 0.000000000000000e0</fractional_translation>
        <equivalent_atoms nat="5" size="5">
          1 2 3 4 5
          </equivalent_atoms>
      </symmetry>
      <symmetry>
        <info name="inv. 180 deg rotation - cart. axis [1,1,0]">crystal_symmetry</info>
        <rotation rank="2" dims="3 3" order="F">
          0.000000000000000e0 -1.000000000000000e0 0.000000000000000e0
          -1.000000000000000e0 0.000000000000000e0 0.000000000000000e0
          0.000000000000000e0 0.000000000000000e0 1.000000000000000e0
          </rotation>
        <fractional_translation>0.000000000000000e0 0.000000000000000e0 0.000000000000000e0</fractional_translation>
        <equivalent_atoms nat="5" size="5">
          1 2 5 4 3
          </equivalent_atoms>
      </symmetry>
      <symmetry>
        <info name="inv. 180 deg rotation - cart. axis [1,-1,0]">crystal_symmetry</info>
        <rotation rank="2" dims="3 3" order="F">
          0.000000000000000e0 1.000000000000000e0 0.000000000000000e0
          1.000000000000000e0 0.000000000000000e0 0.000000000000000e0
          0.000000000000000e0 0.000000000000000e0 1.000000000000000e0
          </rotation>
        <fractional_translation>0.000000000000000e0 0.000000000000000e0 0.000000000000000e0</fractional_translation>
        <equivalent_atoms nat="5" size="5">
          1 2 5 4 3
          </equivalent_atoms>
      </symmetry>
      <symmetry>
        <info name="inv.  90 deg rotation - cart. axis [0,0,-1]">crystal_symmetry</info>
        <rotation rank="2" dims="3 3" order="F">
          0.000000000000000e0 -1.000000000000000e0 0.000000000000000e0
          1.000000000000000e0 0.000000000000000e0 0.000000000000000e0
          0.000000000000000e0 0.000000000000000e0 -1.000000000000000e0
          </rotation>
        <fractional_translation>0.000000000000000e0 0.000000000000000e0 0.000000000000000e0</fractional_translation>
        <equivalent_atoms nat="5" size="5">
          1 2 5 4 3
          </equivalent_atoms>
      </symmetry>
      <symmetry>
        <info name="inv.  90 deg rotation - cart. axis [0,0,1]">crystal_symmetry</info>
        <rotation rank="2" dims="3 3" order="F">
          0.000000000000000e0 1.000000000000000e0 0.000000000000000e0
          -1.000000000000000e0 0.000000000000000e0 0.000000000000000e0
          0.000000000000000e0 0.000000000000000e0 -1.000000000000000e0
          </rotation>
        <fractional_translation>0.000000000000000e0 0.000000000000000e0 0.000000000000000e0</fractional_translation>
        <equivalent_atoms nat="5" size="5">
          1 2 5 4 3
          </equivalent_atoms>
      </symmetry>
      <symmetry>
        <info name="inv. 180 deg rotation - cart. axis [1,0,1]">crystal_symmetry</info>
        <rotation rank="2" dims="3 3" order="F">
          0.000000000000000e0 0.000000000000000e0 -1.000000000000000e0
          0.000000000000000e0 1.000000000000000e0 0.000000000000000e0
          -1.000000000000000e0 0.000000000000000e0 0.000000000000000e0
          </rotation>
        <fractional_translation>0.000000000000000e0 0.000000000000000e0 0.000000000000000e0</fractional_translation>
        <equivalent_atoms nat="5" size="5">
          1 2 3 5 4
          </equivalent_atoms>
      </symmetry>
      <symmetry>
        <info name="inv. 180 deg rotation - cart. axis [-1,0,1]">crystal_symmetry</info>
        <rotation rank="2" dims="3 3" order="F">
          0.000000000000000e0 0.000000000000000e0 1.000000000000000e0
          0.000000000000000e0 1.000000000000000e0 0.000000000000000e0
          1.000000000000000e0 0.000000000000000e0 0.000000000000000e0
          </rotation>
        <fractional_translation>0.000000000000000e0 0.000000000000000e0 0.000000000000000e0</fractional_translation>
        <equivalent_atoms nat="5" size="5">
          1 2 3 5 4
          </equivalent_atoms>
      </symmetry>
      <symmetry>
        <info name="inv.  90 deg rotation - cart. axis [0,1,0]">crystal_symmetry</info>
        <rotation rank="2" dims="3 3" order="F">
          0.000000000000000e0 0.000000000000000e0 -1.000000000000000e0
          0.000000000000000e0 -1.000000000000000e0 0.000000000000000e0
          1.000000000000000e0 0.000000000000000e0 0.000000000000000e0
          </rotation>
        <fractional_translation>0.000000000000000e0 0.000000000000000e0 0.000000000000000e0</fractional_translation>
        <equivalent_atoms nat="5" size="5">
          1 2 3 5 4
          </equivalent_atoms>
      </symmetry>
      <symmetry>
        <info name="inv.  90 deg rotation - cart. axis [0,-1,0]">crystal_symmetry</info>
        <rotation rank="2" dims="3 3" order="F">
          0.000000000000000e0 0.000000000000000e0 1.000000000000000e0
          0.000000000000000e0 -1.000000000000000e0 0.000000000000000e0
          -1.000000000000000e0 0.000000000000000e0 0.000000000000000e0
          </rotation>
        <fractional_translation>0.000000000000000e0 0.000000000000000e0 0.000000000000000e0</fractional_translation>
        <equivalent_atoms nat="5" size="5">
          1 2 3 5 4
          </equivalent_atoms>
      </symmetry>
      <symmetry>
        <info name="inv. 180 deg rotation - cart. axis [0,1,1]">crystal_symmetry</info>
        <rotation rank="2" dims="3 3" order="F">
          1.000000000000000e0 0.000000000000000e0 0.000000000000000e0
          0.000000000000000e0 0.000000000000000e0 -1.000000000000000e0
          0.000000000000000e0 -1.000000000000000e0 0.000000000000000e0
          </rotation>
        <fractional_translation>0.000000000000000e0 0.000000000000000e0 0.000000000000000e0</fractional_translation>
        <equivalent_atoms nat="5" size="5">
          1 2 4 3 5
          </equivalent_atoms>
      </symmetry>
      <symmetry>
        <info name="inv. 180 deg rotation - cart. axis [0,1,-1]">crystal_symmetry</info>
        <rotation rank="2" dims="3 3" order="F">
          1.000000000000000e0 0.000000000000000e0 0.000000000000000e0
          0.000000000000000e0 0.000000000000000e0 1.000000000000000e0
          0.000000000000000e0 1.000000000000000e0 0.000000000000000e0
          </rotation>
        <fractional_translation>0.000000000000000e0 0.000000000000000e0 0.000000000000000e0</fractional_translation>
        <equivalent_atoms nat="5" size="5">
          1 2 4 3 5
          </equivalent_atoms>
      </symmetry>
      <symmetry>
        <info name="inv.  90 deg rotation - cart. axis [-1,0,0]">crystal_symmetry</info>
        <rotation rank="2" dims="3 3" order="F">
          -1.000000000000000e0 0.000000000000000e0 0.000000000000000e0
          0.000000000000000e0 0.000000000000000e0 -1.000000000000000e0
          0.000000000000000e0 1.000000000000000e0 0.000000000000000e0
          </rotation>
        <fractional_translation>0.000000000000000e0 0.000000000000000e0 0.000000000000000e0</fractional_translation>
        <equivalent_atoms nat="5" size="5">
          1 2 4 3 5
          </equivalent_atoms>
      </symmetry>
      <symmetry>
        <info name="inv.  90 deg rotation - cart. axis [1,0,0]">crystal_symmetry</info>
        <rotation rank="2" dims="3 3" order="F">
          -1.000000000000000e0 0.000000000000000e0 0.000000000000000e0
          0.000000000000000e0 0.000000000000000e0 1.000000000000000e0
          0.000000000000000e0 -1.000000000000000e0 0.000000000000000e0
          </rotation>
        <fractional_translation>0.000000000000000e0 0.000000000000000e0 0.000000000000000e0</fractional_translation>
        <equivalent_atoms nat="5" size="5">
          1 2 4 3 5
          </equivalent_atoms>
      </symmetry>
      <symmetry>
        <info name="inv. 120 deg rotation - cart. axis [-1,-1,-1]">crystal_symmetry</info>
        <rotation rank="2" dims="3 3" order="F">
          0.000000000000000e0 -1.000000000000000e0 0.000000000000000e0
          0.000000000000000e0 0.000000000000000e0 -1.000000000000000e0
          -1.000000000000000e0 0.000000000000000e0 0.000000000000000e0
          </rotation>
        <fractional_translation>0.000000000000000e0 0.000000000000000e0 0.000000000000000e0</fractional_translation>
        <equivalent_atoms nat="5" size="5">
          1 2 5 3 4
          </equivalent_atoms>
      </symmetry>
      <symmetry>
        <info name="inv. 120 deg rotation - cart. axis [-1,1,1]">crystal_symmetry</info>
        <rotation rank="2" dims="3 3" order="F">
          0.000000000000000e0 1.000000000000000e0 0.000000000000000e0
          0.000000000000000e0 0.000000000000000e0 -1.000000000000000e0
          1.000000000000000e0 0.000000000000000e0 0.000000000000000e0
          </rotation>
        <fractional_translation>0.000000000000000e0 0.000000000000000e0 0.000000000000000e0</fractional_translation>
        <equivalent_atoms nat="5" size="5">
          1 2 5 3 4
          </equivalent_atoms>
      </symmetry>
      <symmetry>
        <info name="inv. 120 deg rotation - cart. axis [1,1,-1]">crystal_symmetry</info>
        <rotation rank="2" dims="3 3" order="F">
          0.000000000000000e0 -1.000000000000000e0 0.000000000000000e0
          0.000000000000000e0 0.000000000000000e0 1.000000000000000e0
          1.000000000000000e0 0.000000000000000e0 0.000000000000000e0
          </rotation>
        <fractional_translation>0.000000000000000e0 0.000000000000000e0 0.000000000000000e0</fractional_translation>
        <equivalent_atoms nat="5" size="5">
          1 2 5 3 4
          </equivalent_atoms>
      </symmetry>
      <symmetry>
        <info name="inv. 120 deg rotation - cart. axis [1,-1,1]">crystal_symmetry</info>
        <rotation rank="2" dims="3 3" order="F">
          0.000000000000000e0 1.000000000000000e0 0.000000000000000e0
          0.000000000000000e0 0.000000000000000e0 1.000000000000000e0
          -1.000000000000000e0 0.000000000000000e0 0.000000000000000e0
          </rotation>
        <fractional_translation>0.000000000000000e0 0.000000000000000e0 0.000000000000000e0</fractional_translation>
        <equivalent_atoms nat="5" size="5">
          1 2 5 3 4
          </equivalent_atoms>
      </symmetry>
      <symmetry>
        <info name="inv. 120 deg rotation - cart. axis [1,1,1]">crystal_symmetry</info>
        <rotation rank="2" dims="3 3" order="F">
          0.000000000000000e0 0.000000000000000e0 -1.000000000000000e0
          -1.000000000000000e0 0.000000000000000e0 0.000000000000000e0
          0.000000000000000e0 -1.000000000000000e0 0.000000000000000e0
          </rotation>
        <fractional_translation>0.000000000000000e0 0.000000000000000e0 0.000000000000000e0</fractional_translation>
        <equivalent_atoms nat="5" size="5">
          1 2 4 5 3
          </equivalent_atoms>
      </symmetry>
      <symmetry>
        <info name="inv. 120 deg rotation - cart. axis [-1,1,-1]">crystal_symmetry</info>
        <rotation rank="2" dims="3 3" order="F">
          0.000000000000000e0 0.000000000000000e0 -1.000000000000000e0
          1.000000000000000e0 0.000000000000000e0 0.000000000000000e0
          0.000000000000000e0 1.000000000000000e0 0.000000000000000e0
          </rotation>
        <fractional_translation>0.000000000000000e0 0.000000000000000e0 0.000000000000000e0</fractional_translation>
        <equivalent_atoms nat="5" size="5">
          1 2 4 5 3
          </equivalent_atoms>
      </symmetry>
      <symmetry>
        <info name="inv. 120 deg rotation - cart. axis [1,-1,-1]">crystal_symmetry</info>
        <rotation rank="2" dims="3 3" order="F">
          0.000000000000000e0 0.000000000000000e0 1.000000000000000e0
          1.000000000000000e0 0.000000000000000e0 0.000000000000000e0
          0.000000000000000e0 -1.000000000000000e0 0.000000000000000e0
          </rotation>
        <fractional_translation>0.000000000000000e0 0.000000000000000e0 0.000000000000000e0</fractional_translation>
        <equivalent_atoms nat="5" size="5">
          1 2 4 5 3
          </equivalent_atoms>
      </symmetry>
      <symmetry>
        <info name="inv. 120 deg rotation - cart. axis [-1,-1,1]">crystal_symmetry</info>
        <rotation rank="2" dims="3 3" order="F">
          0.000000000000000e0 0.000000000000000e0 1.000000000000000e0
          -1.000000000000000e0 0.000000000000000e0 0.000000000000000e0
          0.000000000000000e0 1.000000000000000e0 0.000000000000000e0
          </rotation>
        <fractional_translation>0.000000000000000e0 0.000000000000000e0 0.000000000000000e0</fractional_translation>
        <equivalent_atoms nat="5" size="5">
          1 2 4 5 3
          </equivalent_atoms>
      </symmetry>
    </symmetries>
    <basis_set>
      <gamma_only>false</gamma_only>
      <ecutwfc>1.050000000000000e2</ecutwfc>
      <ecutrho>4.200000000000000e2</ecutrho>
      <fft_grid nr1="72" nr2="72" nr3="72"></fft_grid>
      <fft_smooth nr1="72" nr2="72" nr3="72"></fft_smooth>
      <fft_box nr1="72" nr2="72" nr3="72"></fft_box>
      <ngm>150555</ngm>
      <ngms>150555</ngms>
      <npwx>18862</npwx>
      <reciprocal_lattice>
        <b1>1.010101010101010e0 0.000000000000000e0 0.000000000000000e0</b1>
        <b2>0.000000000000000e0 1.010101010101010e0 0.000000000000000e0</b2>
        <b3>0.000000000000000e0 0.000000000000000e0 1.010101010101010e0</b3>
      </reciprocal_lattice>
    </basis_set>
    <dft>
      <functional>PZ</functional>
    </dft>
    <magnetization>
      <lsda>false</lsda>
      <noncolin>false</noncolin>
      <spinorbit>false</spinorbit>
      <total>0.000000000000000e0</total>
      <absolute>0.000000000000000e0</absolute>
      <do_magnetization>false</do_magnetization>
    </magnetization>
    <total_energy>
      <etot>-5.270606734217022e1</etot>
      <eband>-1.110195982079023e-1</eband>
      <ehart>1.740265406350229e1</ehart>
      <vtxc>-1.595307901570089e1</vtxc>
      <etxc>-1.217854805060325e1</etxc>
      <ewald>-3.896837258998845e1</ewald>
    </total_energy>
    <band_structure>
      <lsda>false</lsda>
      <noncolin>false</noncolin>
      <spinorbit>false</spinorbit>
      <nbnd>12</nbnd>
      <nelec>2.400000000000000e1</nelec>
      <num_of_atomic_wfc>18</num_of_atomic_wfc>
      <wf_collected>true</wf_collected>
      <highestOccupiedLevel>2.170326952834915e-1</highestOccupiedLevel>
      <starting_k_points>
        <monkhorst_pack nk1="4" nk2="4" nk3="4" k1="1" k2="1" k3="1">Uniform grid with offset</monkhorst_pack>
      </starting_k_points>
      <nks>4</nks>
      <occupations_kind>fixed</occupations_kind>
      <ks_energies>
        <k_point weight="2.500000000000e-1">1.262626262626263e-1 1.262626262626263e-1 1.262626262626263e-1</k_point>
        <npw>18862</npw>
        <eigenvalues size="12">
          -4.215245885367022e-1 -3.777761023928783e-1 -3.777761023352776e-1 8.304360067507849e-2 9.849349902938648e-2
          9.849349912044360e-2 1.431697158474962e-1 1.431697159983517e-1 1.731200472290227e-1 1.842760165632556e-1
          1.919028811623830e-1 1.919028812796545e-1
          </eigenvalues>
        <occupations size="12">
          1.000000000000000e0 1.000000000000000e0 1.000000000000000e0 1.000000000000000e0 1.000000000000000e0
          1.000000000000000e0 1.000000000000000e0 1.000000000000000e0 1.000000000000000e0 1.000000000000000e0
          1.000000000000000e0 1.000000000000000e0
          </occupations>
      </ks_energies>
      <ks_energies>
        <k_point weight="7.500000000000e-1">1.262626262626263e-1 1.262626262626263e-1 3.787878787878788e-1</k_point>
        <npw>18821</npw>
        <eigenvalues size="12">
          -4.053546532740581e-1 -3.766044628266334e-1 -3.737997973207141e-1 5.203801178134350e-2 8.354238026764506e-2
          9.685008854023842e-2 1.007926815521373e-1 1.063418736253482e-1 1.560913901566453e-1 1.708771163099714e-1
          1.732585741309459e-1 1.827504044965919e-1
          </eigenvalues>
        <occupations size="12">
          1.000000000000000e0 1.000000000000000e0 1.000000000000000e0 1.000000000000000e0 1.000000000000000e0
          1.000000000000000e0 1.000000000000000e0 1.000000000000000e0 1.000000000000000e0 1.000000000000000e0
          1.000000000000000e0 1.000000000000000e0
          </occupations>
      </ks_energies>
      <ks_energies>
        <k_point weight="7.500000000000e-1">1.262626262626263e-1 3.787878787878788e-1 3.787878787878788e-1</k_point>
        <npw>18806</npw>
        <eigenvalues size="12">
          -3.952392875862141e-1 -3.724587122853409e-1 -3.700198499032138e-1 4.120332524440667e-2 5.380235592254678e-2
          5.852181052513640e-2 8.984142557177130e-2 9.658558829648072e-2 1.352522377183747e-1 1.675723684770293e-1
          1.710824466356267e-1 2.100092244235447e-1
          </eigenvalues>
        <occupations size="12">
          1.000000000000000e0 1.000000000000000e0 1.000000000000000e0 1.000000000000000e0 1.000000000000000e0
          1.000000000000000e0 1.000000000000000e0 1.000000000000000e0 1.000000000000000e0 1.000000000000000e0
          1.000000000000000e0 1.000000000000000e0
          </occupations>
      </ks_energies>
      <ks_energies>
        <k_point weight="2.500000000000e-1">3.787878787878788e-1 3.787878787878788e-1 3.787878787878788e-1</k_point>
        <npw>18805</npw>
        <eigenvalues size="12">
          -3.797836631724177e-1 -3.722287974589955e-1 -3.722287974588995e-1 4.667548872787240e-2 5.933081878438546e-2
          5.933081879348735e-2 6.324705755343624e-2 6.697417203693958e-2 6.697417205602720e-2 2.056464784712808e-1
          2.056464784727387e-1 2.170326952834915e-1
          </eigenvalues>
        <occupations size="12">
          1.000000000000000e0 1.000000000000000e0 1.000000000000000e0 1.000000000000000e0 1.000000000000000e0
          1.000000000000000e0 1.000000000000000e0 1.000000000000000e0 1.000000000000000e0 1.000000000000000e0
          1.000000000000000e0 1.000000000000000e0
          </occupations>
      </ks_energies>
    </band_structure>
  </output>
  <status>0</status>
  <timing_info>
    <total label="PWSCF">
      <cpu>1.713281250000000e2</cpu>
      <wall>2.861237907409668e1</wall>
    </total>
    <partial label="electrons" calls="1">
      <cpu>1.665468750000000e2</cpu>
      <wall>2.607298302650452e1</wall>
    </partial>
  </timing_info>
  <closed DATE="31 Jul 2021" TIME="15:42:31"></closed>
</qes:espresso>
